awesome_structure/__init__.py
awesome_structure/cli.py
awesome_structure/renderers/__init__.py
awesome_structure/renderers/icons.py
awesome_structure/renderers/markdown.py
awesome_structure/renderers/terminal.py
awesome_structure/tree_builder.py
awesome_structure-0.1.1.dist-info/entry_points.txt
awesome_structure-0.1.1.dist-info/LICENSE
awesome_structure-0.1.1.dist-info/METADATA
awesome_structure-0.1.1.dist-info/WHEEL
awesome_structure-0.1.1.dist-info/RECORD
