Metadata-Version: 2.3
Name: awesome-structure
Version: 0.1.1
Summary: Всего одна команда в терминале, отделяющая вас от наслаждения прекрасной структурой вашего проекта 😌
Keywords: cli,directory,tree,visualization
Author: Dmitry-Peskov
Author-email: dv.peskov@yandex.ru
Requires-Python: >=3.10,<4.0
Classifier: Programming Language :: Python :: 3.10
Classifier: License :: OSI Approved :: MIT License
Classifier: Operating System :: OS Independent
Classifier: Topic :: Utilities
Requires-Dist: click (>=8.1.7,<9.0.0)
